microaligner/__init__.py
microaligner/__main__.py
microaligner/feature_reg/__init__.py
microaligner/feature_reg/feature_detection.py
microaligner/feature_reg/feature_registrator.py
microaligner/feature_reg/tile_registration.py
microaligner/optflow_reg/__init__.py
microaligner/optflow_reg/flow_calc.py
microaligner/optflow_reg/optflow_registrator.py
microaligner/optflow_reg/warper.py
microaligner/pipeline_modules/__init__.py
microaligner/pipeline_modules/config_reader.py
microaligner/pipeline_modules/metadata_handling.py
microaligner/pipeline_modules/ome_meta_processing.py
microaligner/pipeline_modules/stack_builder.py
microaligner/shared_modules/__init__.py
microaligner/shared_modules/dtype_aliases.py
microaligner/shared_modules/img_checks.py
microaligner/shared_modules/similarity_scoring.py
microaligner/shared_modules/slicer.py
microaligner/shared_modules/stitcher.py
microaligner/shared_modules/utils.py
microaligner-1.0.0.data/data/metadata/CITATION.cff
microaligner-1.0.0.data/data/metadata/config_1.yaml
microaligner-1.0.0.data/data/metadata/config_2.yaml
microaligner-1.0.0.data/data/metadata/config_3.yaml
microaligner-1.0.0.data/data/metadata/config_with_all_info.yaml
microaligner-1.0.0.data/data/metadata/environment.yaml
microaligner-1.0.0.dist-info/LICENSE
microaligner-1.0.0.dist-info/METADATA
microaligner-1.0.0.dist-info/WHEEL
microaligner-1.0.0.dist-info/entry_points.txt
microaligner-1.0.0.dist-info/top_level.txt
microaligner-1.0.0.dist-info/RECORD
