Metadata-Version: 2.1
Name: microaligner
Version: 1.0.0
Summary: MicroAligner: image registration for large scale microscopy
Home-page: 
Author: Vasyl Vaskivskyi
Author-email: vaskivskyi.v@gmail.com
License: GPLv3
Project-URL: Source Code, https://github.com/VasylVaskivskyi/microaligner
Platform: any
Classifier: Programming Language :: Python :: 3
Classifier: Development Status :: 5 - Production/Stable
Classifier: Intended Audience :: Science/Research
Classifier: License :: OSI Approved :: GNU General Public License v3 or later (GPLv3+)
Classifier: Operating System :: OS Independent
Classifier: Topic :: Scientific/Engineering :: Image Processing
Requires-Python: >=3.7
License-File: LICENSE
Requires-Dist: numpy (>=1.0)
Requires-Dist: tifffile (>=2020.0)
Requires-Dist: pandas (>=1.0)
Requires-Dist: dask (>=2020.0)
Requires-Dist: scikit-learn (>=1.0)
Requires-Dist: scikit-image (>=0.19)
Requires-Dist: pint (>=0.19.2)
Requires-Dist: opencv-contrib-python (<5.0,>=4.5)
